Metadata-Version: 1.0
Name: distributions-test-avi
Version: 1.0
Summary: Gaussian distributions
Home-page: UNKNOWN
Author: avitomar12
Author-email: avitomar12@gmail.com
License: UNKNOWN
Platform: UNKNOWN
